{
  "resourceType": "Bundle",
  "type": "batch",
  "entry": [
    {
      "resource": {
        "resourceType": "Patient",
        "id": "P001",
        "identifier": [{"system": "http://transitionbridge.ai/patients", "value": "P001"}],
        "name": [{"given": ["Maya"], "family": "Chen"}],
        "birthDate": "2009-03-15",
        "gender": "female"
      },
      "request": {"method": "PUT", "url": "Patient/P001"}
    },
    {
      "resource": {
        "resourceType": "Patient",
        "id": "P002",
        "identifier": [{"system": "http://transitionbridge.ai/patients", "value": "P002"}],
        "name": [{"given": ["Marcus"], "family": "Johnson"}],
        "birthDate": "2010-07-22",
        "gender": "male"
      },
      "request": {"method": "PUT", "url": "Patient/P002"}
    },
    {
      "resource": {
        "resourceType": "Patient",
        "id": "P003",
        "identifier": [{"system": "http://transitionbridge.ai/patients", "value": "P003"}],
        "name": [{"given": ["Sophia"], "family": "Martinez"}],
        "birthDate": "2008-01-10",
        "gender": "female"
      },
      "request": {"method": "PUT", "url": "Patient/P003"}
    },
    {
      "resource": {
        "resourceType": "Patient",
        "id": "P004",
        "identifier": [{"system": "http://transitionbridge.ai/patients", "value": "P004"}],
        "name": [{"given": ["Ethan"], "family": "Williams"}],
        "birthDate": "2010-05-08",
        "gender": "male"
      },
      "request": {"method": "PUT", "url": "Patient/P004"}
    },
    {
      "resource": {
        "resourceType": "Patient",
        "id": "P005",
        "identifier": [{"system": "http://transitionbridge.ai/patients", "value": "P005"}],
        "name": [{"given": ["Aisha"], "family": "Patel"}],
        "birthDate": "2007-09-20",
        "gender": "female"
      },
      "request": {"method": "PUT", "url": "Patient/P005"}
    },
    {
      "resource": {
        "resourceType": "Patient",
        "id": "P006",
        "identifier": [{"system": "http://transitionbridge.ai/patients", "value": "P006"}],
        "name": [{"given": ["Jordan"], "family": "Lee"}],
        "birthDate": "2012-02-14",
        "gender": "male"
      },
      "request": {"method": "PUT", "url": "Patient/P006"}
    },
    {
      "resource": {
        "resourceType": "Patient",
        "id": "P007",
        "identifier": [{"system": "http://transitionbridge.ai/patients", "value": "P007"}],
        "name": [{"given": ["Isabella"], "family": "Rodriguez"}],
        "birthDate": "2009-11-30",
        "gender": "female"
      },
      "request": {"method": "PUT", "url": "Patient/P007"}
    },
    {
      "resource": {
        "resourceType": "Patient",
        "id": "P008",
        "identifier": [{"system": "http://transitionbridge.ai/patients", "value": "P008"}],
        "name": [{"given": ["David"], "family": "Kim"}],
        "birthDate": "2006-04-12",
        "gender": "male"
      },
      "request": {"method": "PUT", "url": "Patient/P008"}
    },
    {
      "resource": {
        "resourceType": "Patient",
        "id": "P009",
        "identifier": [{"system": "http://transitionbridge.ai/patients", "value": "P009"}],
        "name": [{"given": ["Olivia"], "family": "Thompson"}],
        "birthDate": "2013-08-05",
        "gender": "female"
      },
      "request": {"method": "PUT", "url": "Patient/P009"}
    },
    {
      "resource": {
        "resourceType": "Patient",
        "id": "P010",
        "identifier": [{"system": "http://transitionbridge.ai/patients", "value": "P010"}],
        "name": [{"given": ["Noah"], "family": "Brown"}],
        "birthDate": "2010-12-25",
        "gender": "male"
      },
      "request": {"method": "PUT", "url": "Patient/P010"}
    },
    {
      "resource": {
        "resourceType": "Condition",
        "id": "C001",
        "clinicalStatus": {"coding": [{"system": "http://terminology.hl7.org/CodeSystem/condition-clinical", "code": "active"}]},
        "code": {"coding": [{"system": "http://snomed.info/sct", "code": "46635009", "display": "Type 1 diabetes mellitus"}], "text": "Type 1 Diabetes Mellitus"},
        "subject": {"reference": "Patient/P001"},
        "onsetDateTime": "2017-06-01"
      },
      "request": {"method": "PUT", "url": "Condition/C001"}
    },
    {
      "resource": {
        "resourceType": "Condition",
        "id": "C002",
        "clinicalStatus": {"coding": [{"system": "http://terminology.hl7.org/CodeSystem/condition-clinical", "code": "active"}]},
        "code": {"coding": [{"system": "http://snomed.info/sct", "code": "86299006", "display": "Tetralogy of Fallot"}], "text": "Tetralogy of Fallot (repaired)"},
        "subject": {"reference": "Patient/P002"},
        "onsetDateTime": "2010-07-22"
      },
      "request": {"method": "PUT", "url": "Condition/C002"}
    },
    {
      "resource": {
        "resourceType": "Condition",
        "id": "C003",
        "clinicalStatus": {"coding": [{"system": "http://terminology.hl7.org/CodeSystem/condition-clinical", "code": "active"}]},
        "code": {"coding": [{"system": "http://snomed.info/sct", "code": "190905008", "display": "Cystic fibrosis"}], "text": "Cystic Fibrosis"},
        "subject": {"reference": "Patient/P003"},
        "onsetDateTime": "2008-03-15"
      },
      "request": {"method": "PUT", "url": "Condition/C003"}
    },
    {
      "resource": {
        "resourceType": "Condition",
        "id": "C004",
        "clinicalStatus": {"coding": [{"system": "http://terminology.hl7.org/CodeSystem/condition-clinical", "code": "active"}]},
        "code": {"coding": [{"system": "http://snomed.info/sct", "code": "417357006", "display": "Sickle cell disease"}], "text": "Sickle Cell Disease"},
        "subject": {"reference": "Patient/P004"},
        "onsetDateTime": "2010-05-08"
      },
      "request": {"method": "PUT", "url": "Condition/C004"}
    },
    {
      "resource": {
        "resourceType": "Condition",
        "id": "C005",
        "clinicalStatus": {"coding": [{"system": "http://terminology.hl7.org/CodeSystem/condition-clinical", "code": "active"}]},
        "code": {"coding": [{"system": "http://snomed.info/sct", "code": "84757009", "display": "Epilepsy"}], "text": "Epilepsy"},
        "subject": {"reference": "Patient/P005"},
        "onsetDateTime": "2015-03-10"
      },
      "request": {"method": "PUT", "url": "Condition/C005"}
    },
    {
      "resource": {
        "resourceType": "Condition",
        "id": "C006",
        "clinicalStatus": {"coding": [{"system": "http://terminology.hl7.org/CodeSystem/condition-clinical", "code": "active"}]},
        "code": {"coding": [{"system": "http://snomed.info/sct", "code": "410795001", "display": "Juvenile idiopathic arthritis"}], "text": "Juvenile Idiopathic Arthritis"},
        "subject": {"reference": "Patient/P006"},
        "onsetDateTime": "2018-06-15"
      },
      "request": {"method": "PUT", "url": "Condition/C006"}
    },
    {
      "resource": {
        "resourceType": "Condition",
        "id": "C007",
        "clinicalStatus": {"coding": [{"system": "http://terminology.hl7.org/CodeSystem/condition-clinical", "code": "active"}]},
        "code": {"coding": [{"system": "http://snomed.info/sct", "code": "195967001", "display": "Asthma"}], "text": "Severe Persistent Asthma"},
        "subject": {"reference": "Patient/P007"},
        "onsetDateTime": "2014-09-01"
      },
      "request": {"method": "PUT", "url": "Condition/C007"}
    },
    {
      "resource": {
        "resourceType": "Condition",
        "id": "C008",
        "clinicalStatus": {"coding": [{"system": "http://terminology.hl7.org/CodeSystem/condition-clinical", "code": "active"}]},
        "code": {"coding": [{"system": "http://snomed.info/sct", "code": "34000006", "display": "Crohn's disease"}], "text": "Crohn's Disease"},
        "subject": {"reference": "Patient/P008"},
        "onsetDateTime": "2018-11-20"
      },
      "request": {"method": "PUT", "url": "Condition/C008"}
    },
    {
      "resource": {
        "resourceType": "Condition",
        "id": "C009",
        "clinicalStatus": {"coding": [{"system": "http://terminology.hl7.org/CodeSystem/condition-clinical", "code": "active"}]},
        "code": {"coding": [{"system": "http://snomed.info/sct", "code": "406506008", "display": "ADHD"}], "text": "ADHD with Anxiety Disorder"},
        "subject": {"reference": "Patient/P009"},
        "onsetDateTime": "2020-01-15"
      },
      "request": {"method": "PUT", "url": "Condition/C009"}
    },
    {
      "resource": {
        "resourceType": "Condition",
        "id": "C010",
        "clinicalStatus": {"coding": [{"system": "http://terminology.hl7.org/CodeSystem/condition-clinical", "code": "active"}]},
        "code": {"coding": [{"system": "http://snomed.info/sct", "code": "73297009", "display": "Muscular dystrophy"}], "text": "Duchenne Muscular Dystrophy"},
        "subject": {"reference": "Patient/P010"},
        "onsetDateTime": "2014-06-01"
      },
      "request": {"method": "PUT", "url": "Condition/C010"}
    },
    {
      "resource": {
        "resourceType": "Observation",
        "id": "OBS001",
        "status": "final",
        "category": [{"coding": [{"system": "http://terminology.hl7.org/CodeSystem/observation-category", "code": "survey"}]}],
        "code": {"coding": [{"system": "http://loinc.org", "code": "89571-4", "display": "Transition readiness assessment"}], "text": "TRAQ Assessment"},
        "subject": {"reference": "Patient/P001"},
        "effectiveDateTime": "2026-04-01",
        "valueQuantity": {"value": 65, "unit": "%"}
      },
      "request": {"method": "PUT", "url": "Observation/OBS001"}
    },
    {
      "resource": {
        "resourceType": "Observation",
        "id": "OBS002",
        "status": "final",
        "category": [{"coding": [{"system": "http://terminology.hl7.org/CodeSystem/observation-category", "code": "survey"}]}],
        "code": {"coding": [{"system": "http://loinc.org", "code": "89571-4", "display": "Transition readiness assessment"}], "text": "TRAQ Assessment"},
        "subject": {"reference": "Patient/P002"},
        "effectiveDateTime": "2026-04-01",
        "valueQuantity": {"value": 45, "unit": "%"}
      },
      "request": {"method": "PUT", "url": "Observation/OBS002"}
    },
    {
      "resource": {
        "resourceType": "Observation",
        "id": "OBS003",
        "status": "final",
        "category": [{"coding": [{"system": "http://terminology.hl7.org/CodeSystem/observation-category", "code": "survey"}]}],
        "code": {"coding": [{"system": "http://loinc.org", "code": "89571-4", "display": "Transition readiness assessment"}], "text": "TRAQ Assessment"},
        "subject": {"reference": "Patient/P003"},
        "effectiveDateTime": "2026-04-01",
        "valueQuantity": {"value": 78, "unit": "%"}
      },
      "request": {"method": "PUT", "url": "Observation/OBS003"}
    },
    {
      "resource": {
        "resourceType": "Observation",
        "id": "OBS004",
        "status": "final",
        "category": [{"coding": [{"system": "http://terminology.hl7.org/CodeSystem/observation-category", "code": "survey"}]}],
        "code": {"coding": [{"system": "http://loinc.org", "code": "89571-4", "display": "Transition readiness assessment"}], "text": "TRAQ Assessment"},
        "subject": {"reference": "Patient/P004"},
        "effectiveDateTime": "2026-04-01",
        "valueQuantity": {"value": 55, "unit": "%"}
      },
      "request": {"method": "PUT", "url": "Observation/OBS004"}
    },
    {
      "resource": {
        "resourceType": "Observation",
        "id": "OBS005",
        "status": "final",
        "category": [{"coding": [{"system": "http://terminology.hl7.org/CodeSystem/observation-category", "code": "survey"}]}],
        "code": {"coding": [{"system": "http://loinc.org", "code": "89571-4", "display": "Transition readiness assessment"}], "text": "TRAQ Assessment"},
        "subject": {"reference": "Patient/P005"},
        "effectiveDateTime": "2026-04-01",
        "valueQuantity": {"value": 82, "unit": "%"}
      },
      "request": {"method": "PUT", "url": "Observation/OBS005"}
    },
    {
      "resource": {
        "resourceType": "Observation",
        "id": "OBS006",
        "status": "final",
        "category": [{"coding": [{"system": "http://terminology.hl7.org/CodeSystem/observation-category", "code": "survey"}]}],
        "code": {"coding": [{"system": "http://loinc.org", "code": "89571-4", "display": "Transition readiness assessment"}], "text": "TRAQ Assessment"},
        "subject": {"reference": "Patient/P006"},
        "effectiveDateTime": "2026-04-01",
        "valueQuantity": {"value": 35, "unit": "%"}
      },
      "request": {"method": "PUT", "url": "Observation/OBS006"}
    },
    {
      "resource": {
        "resourceType": "Observation",
        "id": "OBS007",
        "status": "final",
        "category": [{"coding": [{"system": "http://terminology.hl7.org/CodeSystem/observation-category", "code": "survey"}]}],
        "code": {"coding": [{"system": "http://loinc.org", "code": "89571-4", "display": "Transition readiness assessment"}], "text": "TRAQ Assessment"},
        "subject": {"reference": "Patient/P007"},
        "effectiveDateTime": "2026-04-01",
        "valueQuantity": {"value": 70, "unit": "%"}
      },
      "request": {"method": "PUT", "url": "Observation/OBS007"}
    },
    {
      "resource": {
        "resourceType": "Observation",
        "id": "OBS008",
        "status": "final",
        "category": [{"coding": [{"system": "http://terminology.hl7.org/CodeSystem/observation-category", "code": "survey"}]}],
        "code": {"coding": [{"system": "http://loinc.org", "code": "89571-4", "display": "Transition readiness assessment"}], "text": "TRAQ Assessment"},
        "subject": {"reference": "Patient/P008"},
        "effectiveDateTime": "2026-04-01",
        "valueQuantity": {"value": 40, "unit": "%"}
      },
      "request": {"method": "PUT", "url": "Observation/OBS008"}
    },
    {
      "resource": {
        "resourceType": "Observation",
        "id": "OBS009",
        "status": "final",
        "category": [{"coding": [{"system": "http://terminology.hl7.org/CodeSystem/observation-category", "code": "survey"}]}],
        "code": {"coding": [{"system": "http://loinc.org", "code": "89571-4", "display": "Transition readiness assessment"}], "text": "TRAQ Assessment"},
        "subject": {"reference": "Patient/P009"},
        "effectiveDateTime": "2026-04-01",
        "valueQuantity": {"value": 25, "unit": "%"}
      },
      "request": {"method": "PUT", "url": "Observation/OBS009"}
    },
    {
      "resource": {
        "resourceType": "Observation",
        "id": "OBS010",
        "status": "final",
        "category": [{"coding": [{"system": "http://terminology.hl7.org/CodeSystem/observation-category", "code": "survey"}]}],
        "code": {"coding": [{"system": "http://loinc.org", "code": "89571-4", "display": "Transition readiness assessment"}], "text": "TRAQ Assessment"},
        "subject": {"reference": "Patient/P010"},
        "effectiveDateTime": "2026-04-01",
        "valueQuantity": {"value": 50, "unit": "%"}
      },
      "request": {"method": "PUT", "url": "Observation/OBS010"}
    },
    {
      "resource": {
        "resourceType": "Practitioner",
        "id": "PROV001",
        "identifier": [{"system": "http://transitionbridge.ai/providers", "value": "PROV-001"}],
        "name": [{"text": "Dr. Sarah Mitchell"}]
      },
      "request": {"method": "PUT", "url": "Practitioner/PROV001"}
    },
    {
      "resource": {
        "resourceType": "Practitioner",
        "id": "PROV002",
        "identifier": [{"system": "http://transitionbridge.ai/providers", "value": "PROV-002"}],
        "name": [{"text": "Dr. James Chen"}]
      },
      "request": {"method": "PUT", "url": "Practitioner/PROV002"}
    },
    {
      "resource": {
        "resourceType": "Practitioner",
        "id": "PROV003",
        "identifier": [{"system": "http://transitionbridge.ai/providers", "value": "PROV-003"}],
        "name": [{"text": "Dr. Amanda Foster"}]
      },
      "request": {"method": "PUT", "url": "Practitioner/PROV003"}
    },
    {
      "resource": {
        "resourceType": "Practitioner",
        "id": "PROV004",
        "identifier": [{"system": "http://transitionbridge.ai/providers", "value": "PROV-004"}],
        "name": [{"text": "Dr. Michael Rivera"}]
      },
      "request": {"method": "PUT", "url": "Practitioner/PROV004"}
    },
    {
      "resource": {
        "resourceType": "Practitioner",
        "id": "PROV005",
        "identifier": [{"system": "http://transitionbridge.ai/providers", "value": "PROV-005"}],
        "name": [{"text": "Dr. Lisa Wang"}]
      },
      "request": {"method": "PUT", "url": "Practitioner/PROV005"}
    },
    {
      "resource": {
        "resourceType": "PractitionerRole",
        "id": "PR001",
        "practitioner": {"reference": "Practitioner/PROV001", "display": "Dr. Sarah Mitchell"},
        "specialty": [{"coding": [{"system": "http://snomed.info/sct", "code": "394583002", "display": "Endocrinology"}], "text": "Endocrinology"}]
      },
      "request": {"method": "PUT", "url": "PractitionerRole/PR001"}
    },
    {
      "resource": {
        "resourceType": "PractitionerRole",
        "id": "PR002",
        "practitioner": {"reference": "Practitioner/PROV002", "display": "Dr. James Chen"},
        "specialty": [{"coding": [{"system": "http://snomed.info/sct", "code": "394579002", "display": "Cardiology"}], "text": "Adult Congenital Heart Disease"}]
      },
      "request": {"method": "PUT", "url": "PractitionerRole/PR002"}
    },
    {
      "resource": {
        "resourceType": "PractitionerRole",
        "id": "PR003",
        "practitioner": {"reference": "Practitioner/PROV003", "display": "Dr. Amanda Foster"},
        "specialty": [{"coding": [{"system": "http://snomed.info/sct", "code": "418112009", "display": "Pulmonology"}], "text": "Pulmonology - CF Center"}]
      },
      "request": {"method": "PUT", "url": "PractitionerRole/PR003"}
    },
    {
      "resource": {
        "resourceType": "PractitionerRole",
        "id": "PR004",
        "practitioner": {"reference": "Practitioner/PROV004", "display": "Dr. Michael Rivera"},
        "specialty": [{"coding": [{"system": "http://snomed.info/sct", "code": "394584008", "display": "Gastroenterology"}], "text": "Gastroenterology - IBD Specialist"}]
      },
      "request": {"method": "PUT", "url": "PractitionerRole/PR004"}
    },
    {
      "resource": {
        "resourceType": "PractitionerRole",
        "id": "PR005",
        "practitioner": {"reference": "Practitioner/PROV005", "display": "Dr. Lisa Wang"},
        "specialty": [{"coding": [{"system": "http://snomed.info/sct", "code": "394591006", "display": "Neurology"}], "text": "Neurology - Epilepsy Center"}]
      },
      "request": {"method": "PUT", "url": "PractitionerRole/PR005"}
    },
    {
      "resource": {
        "resourceType": "CarePlan",
        "id": "CP001",
        "status": "active",
        "intent": "plan",
        "title": "Transition Care Plan - Maya Chen",
        "subject": {"reference": "Patient/P001"},
        "period": {"start": "2026-01-01", "end": "2027-03-15"},
        "description": "Pediatric to adult care transition plan for Type 1 Diabetes management"
      },
      "request": {"method": "PUT", "url": "CarePlan/CP001"}
    },
    {
      "resource": {
        "resourceType": "CarePlan",
        "id": "CP002",
        "status": "active",
        "intent": "plan",
        "title": "Transition Care Plan - Marcus Johnson",
        "subject": {"reference": "Patient/P002"},
        "period": {"start": "2026-01-01", "end": "2028-07-22"},
        "description": "Pediatric to adult care transition plan for congenital heart disease follow-up"
      },
      "request": {"method": "PUT", "url": "CarePlan/CP002"}
    },
    {
      "resource": {
        "resourceType": "CarePlan",
        "id": "CP003",
        "status": "active",
        "intent": "plan",
        "title": "Transition Care Plan - Sophia Martinez",
        "subject": {"reference": "Patient/P003"},
        "period": {"start": "2026-01-01", "end": "2026-06-01"},
        "description": "URGENT: Expedited transition plan for Cystic Fibrosis - patient has aged out"
      },
      "request": {"method": "PUT", "url": "CarePlan/CP003"}
    }
  ]
}
